NetHyTech_DeepTTS/__init__.py
NetHyTech_DeepTTS-1.0.dist-info/METADATA
NetHyTech_DeepTTS-1.0.dist-info/WHEEL
NetHyTech_DeepTTS-1.0.dist-info/entry_points.txt
NetHyTech_DeepTTS-1.0.dist-info/top_level.txt
NetHyTech_DeepTTS-1.0.dist-info/RECORD
