Metadata-Version: 2.1
Name: NetHyTech-DeepTTS
Version: 1.0
Summary: A Python package for text-to-speech conversion using DeepAI API.
Author: Anubhav Chaturvedi
Author-email: chaturvedianubhav520@example.com
Classifier: Development Status :: 5 - Production/Stable
Classifier: Intended Audience :: Developers
Classifier: Topic :: Multimedia :: Sound/Audio :: Speech
Classifier: License :: OSI Approved :: MIT License
Classifier: Programming Language :: Python :: 3
Classifier: Programming Language :: Python :: 3.8
Classifier: Programming Language :: Python :: 3.9
Classifier: Operating System :: OS Independent
Requires-Python: >=3.8
Requires-Dist: playsound
Requires-Dist: requests
